wxworkbot/__init__.py
wxworkbot/core.py
wxworkbot/exceptions.py
wxworkbot-0.0.2.dist-info/METADATA
wxworkbot-0.0.2.dist-info/WHEEL
wxworkbot-0.0.2.dist-info/top_level.txt
wxworkbot-0.0.2.dist-info/RECORD
