Metadata-Version: 2.1
Name: wxworkbot
Version: 0.0.2
Summary: ['WxWork bot API client']
Home-page: UNKNOWN
Author: ahui,haozi
Author-email: ahui@qunhemail.com,haozi@qunhemail.com
License: MIT License
Keywords: WxWork,bot,API
Platform: UNKNOWN
Classifier: Programming Language :: Python :: 3
Classifier: License :: OSI Approved :: MIT License
Classifier: Operating System :: OS Independent
Requires-Python: >=3
Requires-Dist: requests
